localcosmos_server/__init__.py
localcosmos_server/admin.py
localcosmos_server/apps.py
localcosmos_server/context_processors.py
localcosmos_server/decorators.py
localcosmos_server/fields.py
localcosmos_server/forms.py
localcosmos_server/generic_views.py
localcosmos_server/global_urls.py
localcosmos_server/mails.py
localcosmos_server/middleware.py
localcosmos_server/models.py
localcosmos_server/permission_rules.py
localcosmos_server/settings.py
localcosmos_server/setup_forms.py
localcosmos_server/setup_urls.py
localcosmos_server/setup_views.py
localcosmos_server/slugifier.py
localcosmos_server/urls.py
localcosmos_server/utils.py
localcosmos_server/validators.py
localcosmos_server/view_mixins.py
localcosmos_server/views.py
localcosmos_server/widgets.py
localcosmos_server/analytics/__init__.py
localcosmos_server/analytics/admin.py
localcosmos_server/analytics/apps.py
localcosmos_server/analytics/models.py
localcosmos_server/analytics/views.py
localcosmos_server/analytics/api/__init__.py
localcosmos_server/analytics/api/serializers.py
localcosmos_server/analytics/api/urls.py
localcosmos_server/analytics/api/views.py
localcosmos_server/analytics/migrations/0001_initial.py
localcosmos_server/analytics/migrations/__init__.py
localcosmos_server/api/__init__.py
localcosmos_server/api/anycluster_schema_urls.py
localcosmos_server/api/examples.py
localcosmos_server/api/permissions.py
localcosmos_server/api/serializers.py
localcosmos_server/api/urls.py
localcosmos_server/api/views.py
localcosmos_server/api/example_files/taxon_profile.json
localcosmos_server/app_admin/__init__.py
localcosmos_server/app_admin/admin.py
localcosmos_server/app_admin/apps.py
localcosmos_server/app_admin/forms.py
localcosmos_server/app_admin/middleware.py
localcosmos_server/app_admin/models.py
localcosmos_server/app_admin/urls.py
localcosmos_server/app_admin/view_mixins.py
localcosmos_server/app_admin/views.py
localcosmos_server/app_admin/static/app_admin/css/app_admin.css
localcosmos_server-0.24.0.dist-info/licenses/LICENCE
localcosmos_server-0.24.0.dist-info/METADATA
localcosmos_server-0.24.0.dist-info/WHEEL
localcosmos_server-0.24.0.dist-info/top_level.txt
localcosmos_server-0.24.0.dist-info/RECORD
