Metadata-Version: 2.4
Name: localcosmos_server
Version: 0.24.0
Summary: LocalCosmos Private Server. Run your own server for localcosmos.org apps.
Home-page: https://github.com/SiSol-Systems/localcosmos-server
Author: Thomas Uher
Author-email: thomas.uher@sisol-systems.com
License: The MIT License
Keywords: django,localcosmos,localcosmos server,biodiversity
Platform: OS Independent
Classifier: Programming Language :: Python :: 3
Classifier: License :: OSI Approved :: MIT License
Classifier: Operating System :: OS Independent
Requires-Python: >=3.6
License-File: LICENCE
Requires-Dist: django==5.1.7
Requires-Dist: djangorestframework==3.15.2
Requires-Dist: djangorestframework-simplejwt==5.4.0
Requires-Dist: djangorestframework-camel-case==1.4.2
Requires-Dist: drf-spectacular==0.28.0
Requires-Dist: django-imagekit==5.0.0
Requires-Dist: content-licencing
Requires-Dist: anycluster
Requires-Dist: rules==3.5
Requires-Dist: django-el-pagination==4.1.2
Requires-Dist: django-octicons==1.0.2
Requires-Dist: django-countries==7.6.1
Requires-Dist: django-cors-headers==4.6.0
Requires-Dist: Pillow
Requires-Dist: matplotlib
Requires-Dist: django-taggit==6.1.0
Requires-Dist: requests
Dynamic: author
Dynamic: author-email
Dynamic: classifier
Dynamic: description
Dynamic: description-content-type
Dynamic: home-page
Dynamic: keywords
Dynamic: license
Dynamic: license-file
Dynamic: platform
Dynamic: requires-dist
Dynamic: requires-python
Dynamic: summary
